ZiyouruanjianZiyouShehui/README.md
ZiyouruanjianZiyouShehui/__init__.py
ZiyouruanjianZiyouShehui/__main__.py
ZiyouruanjianZiyouShehui/file.epub
ZiyouruanjianZiyouShehui/index.html
ZiyouruanjianZiyouShehui/css/__init__.py
ZiyouruanjianZiyouShehui/css/annotations.css
ZiyouruanjianZiyouShehui/css/main.css
ZiyouruanjianZiyouShehui/css/normalize.css
ZiyouruanjianZiyouShehui/css/popup.css
ZiyouruanjianZiyouShehui/font/__init__.py
ZiyouruanjianZiyouShehui/font/fontello.eot
ZiyouruanjianZiyouShehui/font/fontello.svg
ZiyouruanjianZiyouShehui/font/fontello.ttf
ZiyouruanjianZiyouShehui/font/fontello.woff
ZiyouruanjianZiyouShehui/img/__init__.py
ZiyouruanjianZiyouShehui/img/annotator-glyph-sprite.png
ZiyouruanjianZiyouShehui/img/annotator-icon-sprite.png
ZiyouruanjianZiyouShehui/img/apple-touch-icon.png
ZiyouruanjianZiyouShehui/img/cancelfullscreen.png
ZiyouruanjianZiyouShehui/img/close.png
ZiyouruanjianZiyouShehui/img/fullscreen.png
ZiyouruanjianZiyouShehui/img/loader.gif
ZiyouruanjianZiyouShehui/img/menu-icon.png
ZiyouruanjianZiyouShehui/img/save.png
ZiyouruanjianZiyouShehui/img/saved.png
ZiyouruanjianZiyouShehui/img/settings-s.png
ZiyouruanjianZiyouShehui/img/settings.png
ZiyouruanjianZiyouShehui/img/star.png
ZiyouruanjianZiyouShehui/js/__init__.py
ZiyouruanjianZiyouShehui/js/epub.js
ZiyouruanjianZiyouShehui/js/epub.min.js
ZiyouruanjianZiyouShehui/js/epub.min.map
ZiyouruanjianZiyouShehui/js/hooks.min.js
ZiyouruanjianZiyouShehui/js/hooks.min.map
ZiyouruanjianZiyouShehui/js/reader.js
ZiyouruanjianZiyouShehui/js/reader.js.map
ZiyouruanjianZiyouShehui/js/reader.min.js
ZiyouruanjianZiyouShehui/js/reader.min.map
ZiyouruanjianZiyouShehui/js/hooks/__init__.py
ZiyouruanjianZiyouShehui/js/hooks/extensions/__init__.py
ZiyouruanjianZiyouShehui/js/hooks/extensions/highlight.js
ZiyouruanjianZiyouShehui/js/libs/__init__.py
ZiyouruanjianZiyouShehui/js/libs/jquery.min.js
ZiyouruanjianZiyouShehui/js/libs/localforage.min.js
ZiyouruanjianZiyouShehui/js/libs/screenfull.js
ziyouruanjian_ziyou_shehui-2024.3.3.0.dist-info/METADATA
ziyouruanjian_ziyou_shehui-2024.3.3.0.dist-info/WHEEL
ziyouruanjian_ziyou_shehui-2024.3.3.0.dist-info/entry_points.txt
ziyouruanjian_ziyou_shehui-2024.3.3.0.dist-info/top_level.txt
ziyouruanjian_ziyou_shehui-2024.3.3.0.dist-info/RECORD
